abtree/__init__.py
abtree/validators.py
abtree/abtree/__init__.py
abtree/abtree/forest/forest_manager.py
abtree/abtree/forest/plugin_system.py
abtree/abtree/forest/middleware/__init__.py
abtree/abtree/parser/xml_parser.py
abtree/core/__init__.py
abtree/core/status.py
abtree/engine/__init__.py
abtree/engine/behavior_tree.py
abtree/engine/blackboard.py
abtree/engine/event.py
abtree/engine/tick_manager.py
abtree/forest/__init__.py
abtree/forest/communication.py
abtree/forest/config.py
abtree/forest/core.py
abtree/forest/forest_manager.py
abtree/forest/performance.py
abtree/forest/plugin_system.py
abtree/forest/extensions/__init__.py
abtree/forest/middleware/__init__.py
abtree/nodes/__init__.py
abtree/nodes/action.py
abtree/nodes/base.py
abtree/nodes/composite.py
abtree/nodes/condition.py
abtree/nodes/decorator.py
abtree/parser/__init__.py
abtree/parser/tree_builder.py
abtree/parser/xml_parser.py
abtree/registry/__init__.py
abtree/registry/node_registry.py
abtree/tests/test_forest_extensions.py
abtree/utils/__init__.py
abtree/utils/logger.py
abtree-0.3.12.dist-info/licenses/LICENSE
cli/__init__.py
cli/abtree_cli.py
abtree-0.3.12.dist-info/METADATA
abtree-0.3.12.dist-info/WHEEL
abtree-0.3.12.dist-info/entry_points.txt
abtree-0.3.12.dist-info/top_level.txt
abtree-0.3.12.dist-info/RECORD
