Metadata-Version: 2.4
Name: abtree
Version: 0.3.12
Summary: High-performance asynchronous behavior tree framework with behavior forest collaboration,
Author-email: aipanda <iepanda@outlook.com>
License: MIT License
Project-URL: Homepage, https://github.com/xiongwc/abtree
Project-URL: Repository, https://github.com/xiongwc/abtree
Project-URL: Documentation, https://abtree.readthedocs.io
Project-URL: Issues, https://github.com/xiongwc/abtree/issues
Classifier: Development Status :: 4 - Beta
Classifier: Intended Audience :: Developers
Classifier: License :: OSI Approved :: MIT License
Classifier: Programming Language :: Python :: 3
Classifier: Programming Language :: Python :: 3.8
Classifier: Programming Language :: Python :: 3.9
Classifier: Programming Language :: Python :: 3.10
Classifier: Programming Language :: Python :: 3.11
Classifier: Programming Language :: Python :: 3.12
Classifier: Programming Language :: Python :: 3.13
Classifier: Topic :: Software Development :: Libraries :: Python Modules
Classifier: Topic :: Scientific/Engineering :: Artificial Intelligence
Requires-Python: >=3.8
License-File: LICENSE
Requires-Dist: asyncio
Requires-Dist: typing-extensions>=4.0.0
Requires-Dist: lxml>=4.6.0
Requires-Dist: click>=8.0.0
Provides-Extra: dev
Requires-Dist: pytest>=7.0.0; extra == "dev"
Requires-Dist: pytest-asyncio>=0.21.0; extra == "dev"
Requires-Dist: pytest-cov>=4.0.0; extra == "dev"
Requires-Dist: mypy>=1.0.0; extra == "dev"
Requires-Dist: bandit>=1.7.0; extra == "dev"
Requires-Dist: safety>=2.0.0; extra == "dev"
Requires-Dist: pip-tools>=7.0.0; extra == "dev"
Provides-Extra: cli
Requires-Dist: click>=8.0.0; extra == "cli"
Requires-Dist: rich>=12.0.0; extra == "cli"
Dynamic: license-file
